vivi/__init__.py
vivi/app.js
vivi/app.py
vivi/context.py
vivi/elements.py
vivi/events.py
vivi/hooks.py
vivi/node.py
vivi/paths.py
vivi/test.py
vivi/urls.py
vivi-0.1.1.dist-info/LICENSE
vivi-0.1.1.dist-info/WHEEL
vivi-0.1.1.dist-info/METADATA
vivi-0.1.1.dist-info/RECORD
